{
  "command": "python3 run.py --cleanup",
  "started_at": "2026-05-22T21:07:43.048542+00:00",
  "finished_at": "2026-05-22T21:07:43.320532+00:00",
  "status": "ok",
  "steps": [
    {
      "name": "init_db",
      "details": {},
      "started_at": "2026-05-22T21:07:43.048652+00:00",
      "finished_at": "2026-05-22T21:07:43.050044+00:00",
      "duration_s": 0.001,
      "status": "ok"
    },
    {
      "name": "cleanup",
      "details": {},
      "started_at": "2026-05-22T21:07:43.050054+00:00",
      "finished_at": "2026-05-22T21:07:43.320522+00:00",
      "duration_s": 0.27,
      "status": "ok"
    }
  ],
  "errors": []
}
