{
  "command": "python3 run.py --cleanup",
  "started_at": "2026-05-09T07:05:26.401594+00:00",
  "finished_at": "2026-05-09T07:05:26.816366+00:00",
  "status": "ok",
  "steps": [
    {
      "name": "init_db",
      "details": {},
      "started_at": "2026-05-09T07:05:26.401611+00:00",
      "finished_at": "2026-05-09T07:05:26.405138+00:00",
      "duration_s": 0.004,
      "status": "ok"
    },
    {
      "name": "cleanup",
      "details": {},
      "started_at": "2026-05-09T07:05:26.405174+00:00",
      "finished_at": "2026-05-09T07:05:26.816343+00:00",
      "duration_s": 0.411,
      "status": "ok"
    }
  ],
  "errors": []
}
