{
  "command": "python3 run.py --cleanup",
  "started_at": "2026-06-02T22:22:07.130156+00:00",
  "finished_at": "2026-06-02T22:22:07.448225+00:00",
  "status": "ok",
  "steps": [
    {
      "name": "init_db",
      "details": {},
      "started_at": "2026-06-02T22:22:07.130272+00:00",
      "finished_at": "2026-06-02T22:22:07.131732+00:00",
      "duration_s": 0.001,
      "status": "ok"
    },
    {
      "name": "cleanup",
      "details": {},
      "started_at": "2026-06-02T22:22:07.131741+00:00",
      "finished_at": "2026-06-02T22:22:07.448214+00:00",
      "duration_s": 0.316,
      "status": "ok"
    }
  ],
  "errors": []
}
