{
  "command": "python3 run.py --cleanup",
  "started_at": "2026-04-30T22:53:47.745615+00:00",
  "finished_at": "2026-04-30T22:53:48.171931+00:00",
  "status": "ok",
  "steps": [
    {
      "name": "init_db",
      "details": {},
      "started_at": "2026-04-30T22:53:47.745640+00:00",
      "finished_at": "2026-04-30T22:53:47.749007+00:00",
      "duration_s": 0.003,
      "status": "ok"
    },
    {
      "name": "cleanup",
      "details": {},
      "started_at": "2026-04-30T22:53:47.749048+00:00",
      "finished_at": "2026-04-30T22:53:48.171903+00:00",
      "duration_s": 0.423,
      "status": "ok"
    }
  ],
  "errors": []
}
