{
  "command": "python3 run.py --cleanup",
  "started_at": "2026-04-30T20:55:46.329050+00:00",
  "finished_at": "2026-04-30T20:55:46.548866+00:00",
  "status": "ok",
  "steps": [
    {
      "name": "init_db",
      "details": {},
      "started_at": "2026-04-30T20:55:46.329151+00:00",
      "finished_at": "2026-04-30T20:55:46.330576+00:00",
      "duration_s": 0.001,
      "status": "ok"
    },
    {
      "name": "cleanup",
      "details": {},
      "started_at": "2026-04-30T20:55:46.330586+00:00",
      "finished_at": "2026-04-30T20:55:46.548857+00:00",
      "duration_s": 0.218,
      "status": "ok"
    }
  ],
  "errors": []
}
