{
  "command": "python3 run.py --cleanup",
  "started_at": "2026-06-01T06:52:17.129208+00:00",
  "finished_at": "2026-06-01T06:52:17.449094+00:00",
  "status": "ok",
  "steps": [
    {
      "name": "init_db",
      "details": {},
      "started_at": "2026-06-01T06:52:17.129324+00:00",
      "finished_at": "2026-06-01T06:52:17.130786+00:00",
      "duration_s": 0.001,
      "status": "ok"
    },
    {
      "name": "cleanup",
      "details": {},
      "started_at": "2026-06-01T06:52:17.130795+00:00",
      "finished_at": "2026-06-01T06:52:17.449082+00:00",
      "duration_s": 0.318,
      "status": "ok"
    }
  ],
  "errors": []
}
