{
  "command": "python3 run.py --cleanup",
  "started_at": "2026-03-27T11:36:19.725703+00:00",
  "finished_at": "2026-03-27T11:36:19.918295+00:00",
  "status": "ok",
  "steps": [
    {
      "name": "init_db",
      "details": {},
      "started_at": "2026-03-27T11:36:19.725724+00:00",
      "finished_at": "2026-03-27T11:36:19.728916+00:00",
      "duration_s": 0.003,
      "status": "ok"
    },
    {
      "name": "cleanup",
      "details": {},
      "started_at": "2026-03-27T11:36:19.728945+00:00",
      "finished_at": "2026-03-27T11:36:19.918267+00:00",
      "duration_s": 0.189,
      "status": "ok"
    }
  ],
  "errors": []
}
